smtoolkit/__init__.py
smtoolkit/sklearn/__init__.py
smtoolkit/sklearn/processing.py
sagemaker_mlops_toolkit-0.1.0.dev1.dist-info/LICENSE
sagemaker_mlops_toolkit-0.1.0.dev1.dist-info/WHEEL
sagemaker_mlops_toolkit-0.1.0.dev1.dist-info/METADATA
sagemaker_mlops_toolkit-0.1.0.dev1.dist-info/RECORD
